ome_writers/__init__.py
ome_writers/_frame_encoder.py
ome_writers/_memory.py
ome_writers/_router.py
ome_writers/_schema.py
ome_writers/_stream.py
ome_writers/_units.py
ome_writers/_useq.py
ome_writers/_util.py
ome_writers/py.typed
ome_writers/_backends/__init__.py
ome_writers/_backends/_acquire_zarr.py
ome_writers/_backends/_backend.py
ome_writers/_backends/_chunk_buffer.py
ome_writers/_backends/_ome_xml.py
ome_writers/_backends/_tensorstore.py
ome_writers/_backends/_tifffile.py
ome_writers/_backends/_yaozarrs.py
ome_writers/_backends/_zarr_python.py
ome_writers-0.1.0rc2.dist-info/METADATA
ome_writers-0.1.0rc2.dist-info/WHEEL
ome_writers-0.1.0rc2.dist-info/licenses/LICENSE
ome_writers-0.1.0rc2.dist-info/RECORD
