Metadata-Version: 2.4
Name: ome-writers
Version: 0.1.0rc2
Summary: OME-TIFF and OME-ZARR writer APIs designed for microscopy acquisition
Project-URL: homepage, https://github.com/pymmcore-plus/ome-writers
Project-URL: repository, https://github.com/pymmcore-plus/ome-writers
License: BSD-3-Clause
License-File: LICENSE
Classifier: Development Status :: 4 - Beta
Classifier: License :: OSI Approved :: BSD License
Classifier: Programming Language :: Python :: 3
Classifier: Programming Language :: Python :: 3.10
Classifier: Programming Language :: Python :: 3.11
Classifier: Programming Language :: Python :: 3.12
Classifier: Programming Language :: Python :: 3.13
Classifier: Programming Language :: Python :: 3.14
Classifier: Typing :: Typed
Requires-Python: >=3.10
Requires-Dist: numpy>=2
Requires-Dist: pydantic-extra-types>=2.11.0
Requires-Dist: pydantic>=2.8
Requires-Dist: typing-extensions>=4.10.0
Requires-Dist: yaozarrs[io]>=0.2.0
Provides-Extra: acquire-zarr
Requires-Dist: acquire-zarr>=0.6.0; (python_version < '3.14') and extra == 'acquire-zarr'
Provides-Extra: all
Requires-Dist: acquire-zarr>=0.6.0; (python_version < '3.14') and extra == 'all'
Requires-Dist: imagecodecs>=2024.9.22; extra == 'all'
Requires-Dist: ome-types>=0.6.1; extra == 'all'
Requires-Dist: pydantic>=2.8; extra == 'all'
Requires-Dist: tensorstore>=0.1.80; (python_version >= '3.11') and extra == 'all'
Requires-Dist: tifffile>=2024.8.30; extra == 'all'
Requires-Dist: yaozarrs[write-tensorstore]>=0.2.0; extra == 'all'
Requires-Dist: yaozarrs[write-zarr]>=0.2.0; extra == 'all'
Requires-Dist: zarrs>=0.2.1; (python_version >= '3.11') and extra == 'all'
Provides-Extra: tensorstore
Requires-Dist: tensorstore>=0.1.80; (python_version >= '3.11') and extra == 'tensorstore'
Requires-Dist: yaozarrs[write-tensorstore]>=0.2.0; extra == 'tensorstore'
Provides-Extra: tifffile
Requires-Dist: imagecodecs>=2024.9.22; extra == 'tifffile'
Requires-Dist: ome-types>=0.6.1; extra == 'tifffile'
Requires-Dist: pydantic>=2.8; extra == 'tifffile'
Requires-Dist: tifffile>=2024.8.30; extra == 'tifffile'
Provides-Extra: zarr-python
Requires-Dist: yaozarrs[write-zarr]>=0.2.0; extra == 'zarr-python'
Provides-Extra: zarrs-python
Requires-Dist: yaozarrs[write-zarr]>=0.2.0; extra == 'zarrs-python'
Requires-Dist: zarrs>=0.2.1; (python_version >= '3.11') and extra == 'zarrs-python'
